nr_common_metadata/__init__.py
nr_common_metadata/ext.py
nr_common_metadata/models/__init__.py
nr_common_metadata/models/nr_common_metadata.yaml
nr_common_metadata/models/nr_common_metadata_model.yaml
nr_common_metadata/theme/__init__.py
nr_common_metadata/theme/views.py
nr_common_metadata/theme/webpack.py
nr_common_metadata-4.0.0.dev15.dist-info/METADATA
nr_common_metadata-4.0.0.dev15.dist-info/WHEEL
nr_common_metadata-4.0.0.dev15.dist-info/entry_points.txt
nr_common_metadata-4.0.0.dev15.dist-info/top_level.txt
nr_common_metadata-4.0.0.dev15.dist-info/RECORD
