Metadata-Version: 2.1
Name: nr-common-metadata
Version: 4.0.0.dev15
Summary: NR common metadata types
Home-page: https://github.com/NarodniRepozitar/nr-common-metadata
Author: CESNET
Author-email: bauer@cesnet.cz
License: MIT
Keywords: National Repository common model Invenio
Platform: any
Classifier: Development Status :: 5 - Production/Stable
Provides-Extra: tests
Requires-Dist: pytest (>=5.0.0) ; extra == 'tests'
Requires-Dist: pytest-cov (>=2.10.1) ; extra == 'tests'
Requires-Dist: pytest-runner (>=5.3.0) ; extra == 'tests'
